icegrams-1.1.6.dist-info/RECORD
icegrams-1.1.6.dist-info/WHEEL
icegrams-1.1.6.dist-info/top_level.txt
icegrams-1.1.6.dist-info/METADATA
icegrams-1.1.6.dist-info/licenses/LICENSE.txt
icegrams/ngrams.py
icegrams/trie.cpp
icegrams/__init__.py
icegrams/trie_build.py
icegrams/py.typed
icegrams/trie.py
icegrams/trie.h
icegrams/_trie.pypy311-pp73-darwin.so
icegrams/resources/trigrams.bin
